trg/__main__.py
trg/game.py
trg/game_input.py
trg/game_map.py
trg/inventory.py
trg/item.py
trg/main.py
trg/player.py
trg/terminal.py
trg/type.py
trg/data/map.txt
trg_game-0.0.2.dist-info/LICENSE
trg_game-0.0.2.dist-info/METADATA
trg_game-0.0.2.dist-info/WHEEL
trg_game-0.0.2.dist-info/entry_points.txt
trg_game-0.0.2.dist-info/top_level.txt
trg_game-0.0.2.dist-info/RECORD
