Metadata-Version: 2.1
Name: trg-game
Version: 0.0.2
Summary: A terminal RPG
Author-email: Tal <talwat321@gmail.com>
Project-URL: Homepage, https://github.com/talwat/TRG
Project-URL: Bug Tracker, https://github.com/talwat/TRG/issues
Classifier: Programming Language :: Python :: 3
Classifier: License :: OSI Approved :: MIT License
Classifier: Operating System :: OS Independent
Requires-Python: >=3.9
License-File: LICENSE
Requires-Dist: readchar
